{
  "generated_at": "2026-06-22T09:08:51.410968+00:00",
  "lookback_hours": 24,
  "include_retweets": true,
  "handles": [
    "dombaeth27",
    "ryker_crypto"
  ],
  "tweets": {
    "dombaeth27": [
      {
        "text": "Insight telegram publik:  -  \"disini.\"",
        "quote_text": "",
        "quote_author": "",
        "timestamp": "2026-06-22T09:04:23.000Z",
        "permalink": "https://x.com/DombaEth27/status/2068983426527674751",
        "is_pinned": false,
        "is_retweet": false,
        "has_media": false,
        "social_context": "",
        "reply_label": "0 Replies. Reply",
        "retweet_label": "0 reposts. Repost",
        "like_label": "1 Like. Like",
        "snapshot": null
      },
      {
        "text": "RT @m4rsiegbaby: @DombaEth27 @ZetsuInsight Ngikut …",
        "quote_text": "",
        "quote_author": "",
        "timestamp": "2026-06-22T09:02:38.000Z",
        "permalink": "https://x.com/DombaEth27/status/2068982987161846116",
        "is_pinned": false,
        "is_retweet": false,
        "has_media": false,
        "social_context": "",
        "reply_label": "0 Replies. Reply",
        "retweet_label": "0 reposts. Repost",
        "like_label": "0 Likes. Like",
        "snapshot": null
      },
      {
        "text": "Full target \n$EIGEN\n !! harusnya minggu kemarin m, sudah bener \"all in\" \n$AERO\n dan \n$EIGEN\n yah haha \n\nNext Play, hold lebih kuat hehe \n\n$EIGEN\n pump it, +104% dalam beberapa hari.\n\nNext pump berikutnya, jatuh kepada ?",
        "quote_text": "Real fact: crypto trader!!\n\nEven if you bought $EIGEN at the bottom? Would you still hold until the next pump happens?\n\nNot necessarily, you've probably already paper handed!!\n$EIGEN up +82% from early June 2026.\n\nI've already dumped it and bought a bunch of altcoins that I think x.com/dombaeth27/sta…",
        "quote_author": "@DombaEth27",
        "timestamp": "2026-06-22T09:02:23.000Z",
        "permalink": "https://x.com/DombaEth27/status/2068982925149061605",
        "is_pinned": false,
        "is_retweet": false,
        "has_media": true,
        "social_context": "",
        "reply_label": "4 Replies. Reply",
        "retweet_label": "0 reposts. Repost",
        "like_label": "6 Likes. Like",
        "snapshot": null
      },
      {
        "text": "Katakan pada diri kita sendiri !!\n\n\"Saya akan d…",
        "quote_text": "",
        "quote_author": "",
        "timestamp": "2026-06-22T08:55:55.000Z",
        "permalink": "https://x.com/DombaEth27/status/2068981298308448313",
        "is_pinned": false,
        "is_retweet": false,
        "has_media": false,
        "social_context": "",
        "reply_label": "7 Replies. Reply",
        "retweet_label": "0 reposts. Repost",
        "like_label": "7 Likes. Like",
        "snapshot": null
      },
      {
        "text": "Kentut sedang memasak   $…",
        "quote_text": "",
        "quote_author": "",
        "timestamp": "2026-06-22T08:52:16.000Z",
        "permalink": "https://x.com/DombaEth27/status/2068980376106942539",
        "is_pinned": false,
        "is_retweet": false,
        "has_media": false,
        "social_context": "",
        "reply_label": "1 Reply. Reply",
        "retweet_label": "0 reposts. Repost",
        "like_label": "2 Likes. Like",
        "snapshot": null
      },
      {
        "text": "Altcoin Gems: $EIGEN naik +104% \n\nAsataga, seh…",
        "quote_text": "",
        "quote_author": "",
        "timestamp": "2026-06-22T08:48:31.000Z",
        "permalink": "https://x.com/DombaEth27/status/2068979433424506968",
        "is_pinned": false,
        "is_retweet": false,
        "has_media": false,
        "social_context": "",
        "reply_label": "11 Replies. Reply",
        "retweet_label": "0 reposts. Repost",
        "like_label": "7 Likes. Like",
        "snapshot": null
      },
      {
        "text": "BREAKING :\n\nJangan lengah, harga $SOL terus naik !…",
        "quote_text": "",
        "quote_author": "",
        "timestamp": "2026-06-22T08:40:25.000Z",
        "permalink": "https://x.com/DombaEth27/status/2068977397207294044",
        "is_pinned": false,
        "is_retweet": false,
        "has_media": false,
        "social_context": "",
        "reply_label": "3 Replies. Reply",
        "retweet_label": "0 reposts. Repost",
        "like_label": "4 Likes. Like",
        "snapshot": null
      },
      {
        "text": "RT @DombaEth27: UPDATE : Portofolio Subscribsion X…",
        "quote_text": "",
        "quote_author": "",
        "timestamp": "2026-06-22T07:17:42.000Z",
        "permalink": "https://x.com/DombaEth27/status/2068956577588252874",
        "is_pinned": false,
        "is_retweet": false,
        "has_media": false,
        "social_context": "",
        "reply_label": "0 Replies. Reply",
        "retweet_label": "0 reposts. Repost",
        "like_label": "0 Likes. Like",
        "snapshot": null
      },
      {
        "text": "Update: memecoin gems $GOAT \n\nBuy and Hold …",
        "quote_text": "",
        "quote_author": "",
        "timestamp": "2026-06-22T07:17:27.000Z",
        "permalink": "https://x.com/DombaEth27/status/2068956516535955624",
        "is_pinned": false,
        "is_retweet": false,
        "has_media": false,
        "social_context": "",
        "reply_label": "1 Reply. Reply",
        "retweet_label": "0 reposts. Repost",
        "like_label": "7 Likes. Like",
        "snapshot": null
      },
      {
        "text": "𝕏 continues to remove bots from the system. \n\nA big bot purge happened again today. If you've lost some followers, don't worry!\n\nIt's good for your account in the long run.",
        "quote_text": "",
        "quote_author": "",
        "timestamp": "2026-06-22T05:52:01.000Z",
        "permalink": "https://x.com/cb_doge/status/2068935017452146872",
        "is_pinned": false,
        "is_retweet": true,
        "has_media": true,
        "social_context": "Domba.Eth reposted",
        "reply_label": "656 Replies. Reply",
        "retweet_label": "633 reposts. Repost",
        "like_label": "1808 Likes. Like",
        "snapshot": null
      },
      {
        "text": "",
        "quote_text": "",
        "quote_author": "",
        "timestamp": "2026-06-22T05:34:33.000Z",
        "permalink": "https://x.com/DombaEth27/status/2068930620831719911",
        "is_pinned": false,
        "is_retweet": false,
        "has_media": false,
        "social_context": "",
        "reply_label": "5 Replies. Reply",
        "retweet_label": "0 reposts. Repost",
        "like_label": "3 Likes. Like",
        "snapshot": "x_snapshots/dombaeth27_2068930620831719911.png"
      },
      {
        "text": "",
        "quote_text": "",
        "quote_author": "",
        "timestamp": "2026-06-22T05:29:55.000Z",
        "permalink": "https://x.com/DombaEth27/status/2068929455972897173",
        "is_pinned": false,
        "is_retweet": false,
        "has_media": false,
        "social_context": "",
        "reply_label": "9 Replies. Reply",
        "retweet_label": "0 reposts. Repost",
        "like_label": "12 Likes. Like",
        "snapshot": "x_snapshots/dombaeth27_2068929455972897173.png"
      },
      {
        "text": "Alpha $ENA dari bro: @shvalka…",
        "quote_text": "",
        "quote_author": "",
        "timestamp": "2026-06-22T05:25:56.000Z",
        "permalink": "https://x.com/DombaEth27/status/2068928453655814323",
        "is_pinned": false,
        "is_retweet": false,
        "has_media": false,
        "social_context": "",
        "reply_label": "3 Replies. Reply",
        "retweet_label": "0 reposts. Repost",
        "like_label": "8 Likes. Like",
        "snapshot": null
      },
      {
        "text": "",
        "quote_text": "",
        "quote_author": "",
        "timestamp": "2026-06-22T02:56:40.000Z",
        "permalink": "https://x.com/DombaEth27/status/2068890888290685054",
        "is_pinned": false,
        "is_retweet": false,
        "has_media": false,
        "social_context": "",
        "reply_label": "1 Reply. Reply",
        "retweet_label": "0 reposts. Repost",
        "like_label": "4 Likes. Like",
        "snapshot": "x_snapshots/dombaeth27_2068890888290685054.png"
      },
      {
        "text": "BREAKING: $ENA naik tanpa bers…",
        "quote_text": "",
        "quote_author": "",
        "timestamp": "2026-06-22T02:51:07.000Z",
        "permalink": "https://x.com/DombaEth27/status/2068889492220789158",
        "is_pinned": false,
        "is_retweet": false,
        "has_media": false,
        "social_context": "",
        "reply_label": "11 Replies. Reply",
        "retweet_label": "0 reposts. Repost",
        "like_label": "7 Likes. Like",
        "snapshot": null
      },
      {
        "text": "Looks like X is full of bugs again",
        "quote_text": "",
        "quote_author": "",
        "timestamp": "2026-06-22T02:43:20.000Z",
        "permalink": "https://x.com/DombaEth27/status/2068887533648572480",
        "is_pinned": false,
        "is_retweet": false,
        "has_media": false,
        "social_context": "",
        "reply_label": "8 Replies. Reply",
        "retweet_label": "1 repost. Repost",
        "like_label": "10 Likes. Like",
        "snapshot": null
      },
      {
        "text": "BREAKING NEWS: $FET (\n@Fetch_ai\n) \n\n$FET or \n@Fetch_ai\n will launch Agent Launch, the world's first agentic token launch platform.\n\nWhy is this exciting?\n\nAgent Launch enables verified AI Agents from Agentverse AI to launch their own tokens.\n\nBuilt on $BNB Chain: (\n@BNBCHAIN\n)",
        "quote_text": "Yesterday we bought $CHILLGUY  \nToday we're profiting from $CHILLGUY  \n\nAll the alpha is in the subscription, yeah.  \n(sub x: login via browser). x.com/dombaeth27/sta…",
        "quote_author": "@DombaEth27",
        "timestamp": "2026-06-22T02:40:06.000Z",
        "permalink": "https://x.com/DombaEth27/status/2068886719802573060",
        "is_pinned": false,
        "is_retweet": true,
        "has_media": true,
        "social_context": "Domba.Eth reposted",
        "reply_label": "5 Replies. Reply",
        "retweet_label": "1 repost. Repost",
        "like_label": "22 Likes. Like",
        "snapshot": null
      },
      {
        "text": "BREAKING: How to SUB (via browser).\n\nHello! The correct & fast way to subscribe to X Subscription to minimize delay:\n\n1. Open Chrome browser, login \nhttp://\nx.com\n/\n.\n2. Visit the creator's profile.\n3. Click the Subscribe button (top right corner or on the locked post).\n4.",
        "quote_text": "Hello! The correct & quick way to subscribe to X Subscription to minimize delay:\n\n1. Open Chrome browser, login \nhttp://\nx.com.\n2. Visit the creator's profile.\n3. Click the Subscribe button (top right corner or on a locked post).\n4. Follow payment via X.\n\nIt usually",
        "quote_author": "@grok",
        "timestamp": "2026-06-22T01:56:47.000Z",
        "permalink": "https://x.com/DombaEth27/status/2068875817955045519",
        "is_pinned": false,
        "is_retweet": true,
        "has_media": true,
        "social_context": "Domba.Eth reposted",
        "reply_label": "4 Replies. Reply",
        "retweet_label": "0 reposts. Repost",
        "like_label": "7 Likes. Like",
        "snapshot": null
      },
      {
        "text": "90% already secured. Thx om domba.. the best indeed!!!!",
        "quote_text": "",
        "quote_author": "",
        "timestamp": "2026-06-21T16:48:31.000Z",
        "permalink": "https://x.com/tuadiluar/status/2068737842801762677",
        "is_pinned": false,
        "is_retweet": true,
        "has_media": true,
        "social_context": "Domba.Eth reposted",
        "reply_label": "1 Reply. Reply",
        "retweet_label": "1 repost. Repost",
        "like_label": "2 Likes. Like",
        "snapshot": null
      }
    ],
    "ryker_crypto": [
      {
        "text": "CZ is now following me on X , so I will refrain fr…",
        "quote_text": "",
        "quote_author": "",
        "timestamp": "2026-06-22T08:31:17.000Z",
        "permalink": "https://x.com/Ryker_Crypto/status/2068975096358994300",
        "is_pinned": false,
        "is_retweet": false,
        "has_media": false,
        "social_context": "",
        "reply_label": "10 Replies. Reply",
        "retweet_label": "0 reposts. Repost",
        "like_label": "49 Likes. Like",
        "snapshot": null
      },
      {
        "text": "Is anyone still holding a short position on \n$GOLD\n ?",
        "quote_text": "I'm shorting $GOLD \nVery risk trade !  x.com/Ryker_Crypto/s…",
        "quote_author": "@Ryker_Crypto",
        "timestamp": "2026-06-22T07:21:47.000Z",
        "permalink": "https://x.com/Ryker_Crypto/status/2068957608149717451",
        "is_pinned": false,
        "is_retweet": false,
        "has_media": true,
        "social_context": "",
        "reply_label": "45 Replies. Reply",
        "retweet_label": "12 reposts. Repost",
        "like_label": "136 Likes. Like",
        "snapshot": null
      },
      {
        "text": "I can't believe it.\n\nCZ followed me \n\nAm I dreaming, or is this real?\n\nSomeone please tell me ....",
        "quote_text": "$1000 Giveaway for my followers\n\nIn just one month, my X account increased from 10,000 followers to 60,000 followers.\n\nI am truly grateful to everyone who has supported me. I am very happy to be able to share important information and knowledge about Crypto with you all.\n\nSome",
        "quote_author": "@Ryker_Crypto",
        "timestamp": "2026-06-22T03:49:16.000Z",
        "permalink": "https://x.com/Ryker_Crypto/status/2068904126629744923",
        "is_pinned": false,
        "is_retweet": false,
        "has_media": true,
        "social_context": "",
        "reply_label": "218 Replies. Reply",
        "retweet_label": "41 reposts. Repost",
        "like_label": "485 Likes. Like",
        "snapshot": null
      },
      {
        "text": "I earn $7,000 a month from my regular job.\n\nI use $5,000 to invest and trade in crypto.\n\nI use $2,000 for my monthly living expenses.\n\nAnd that has been my life for the past 7 years.",
        "quote_text": "",
        "quote_author": "",
        "timestamp": "2026-06-22T03:09:25.000Z",
        "permalink": "https://x.com/Ryker_Crypto/status/2068894097948180929",
        "is_pinned": false,
        "is_retweet": false,
        "has_media": false,
        "social_context": "",
        "reply_label": "101 Replies. Reply",
        "retweet_label": "21 reposts. Repost",
        "like_label": "386 Likes. Like",
        "snapshot": null
      },
      {
        "text": "Never short shitcoin like \n$TNSR\n \n\nVery risk , be careful",
        "quote_text": "",
        "quote_author": "",
        "timestamp": "2026-06-21T17:13:00.000Z",
        "permalink": "https://x.com/Ryker_Crypto/status/2068744004641137057",
        "is_pinned": false,
        "is_retweet": false,
        "has_media": true,
        "social_context": "",
        "reply_label": "62 Replies. Reply",
        "retweet_label": "24 reposts. Repost",
        "like_label": "269 Likes. Like",
        "snapshot": null
      },
      {
        "text": "I'm long $TNSR \n\nI'm think it will kill…",
        "quote_text": "",
        "quote_author": "",
        "timestamp": "2026-06-21T16:10:01.000Z",
        "permalink": "https://x.com/Ryker_Crypto/status/2068728153087136156",
        "is_pinned": false,
        "is_retweet": false,
        "has_media": false,
        "social_context": "",
        "reply_label": "11 Replies. Reply",
        "retweet_label": "0 reposts. Repost",
        "like_label": "30 Likes. Like",
        "snapshot": null
      },
      {
        "text": "I'm bought more it \n\nI'm think it will pump in the next few days\n\nSend $TRUTH to $0.1\n\nIf \n$SUI\n up about 20%, the $TRUTH team will push the price up min 200%",
        "quote_text": "Last time , I made +270% profit from $US\n\nNow , I'm bought some $TRUTH \n\n$US and $TRUTH are the good project on SUI ecosystem \n\nSend $TRUTH higher !  x.com/ryker_crypto/s…",
        "quote_author": "@Ryker_Crypto",
        "timestamp": "2026-06-21T15:42:16.000Z",
        "permalink": "https://x.com/Ryker_Crypto/status/2068721171378614761",
        "is_pinned": false,
        "is_retweet": false,
        "has_media": true,
        "social_context": "",
        "reply_label": "58 Replies. Reply",
        "retweet_label": "50 reposts. Repost",
        "like_label": "350 Likes. Like",
        "snapshot": null
      },
      {
        "text": "I'm think it will pump in the next few days\n\nW cha…",
        "quote_text": "",
        "quote_author": "",
        "timestamp": "2026-06-21T15:26:44.000Z",
        "permalink": "https://x.com/Ryker_Crypto/status/2068717262006337609",
        "is_pinned": false,
        "is_retweet": false,
        "has_media": false,
        "social_context": "",
        "reply_label": "7 Replies. Reply",
        "retweet_label": "0 reposts. Repost",
        "like_label": "41 Likes. Like",
        "snapshot": null
      },
      {
        "text": "Never ignore Ryker's warning.\n\nI said that chart just fake break out \n\nI’ve seen so many people lose money on $OPN.\n\nI hope you all learn from this experience.",
        "quote_text": "Although the $OPN team is eager to pump the price before the World Cup and the Polymarket TGE, the current FOMO situation makes it very difficult for them.\n\nIn my experience, this is just a fake breakout; it will take a lot of time for the team to accumulate tokens again and  x.com/Ryker_Crypto/s…",
        "quote_author": "@Ryker_Crypto",
        "timestamp": "2026-06-21T11:30:07.000Z",
        "permalink": "https://x.com/Ryker_Crypto/status/2068657715392745488",
        "is_pinned": false,
        "is_retweet": false,
        "has_media": true,
        "social_context": "",
        "reply_label": "74 Replies. Reply",
        "retweet_label": "28 reposts. Repost",
        "like_label": "283 Likes. Like",
        "snapshot": null
      }
    ]
  },
  "errors": {}
}